LICENSE
MANIFEST.in
README.md
setup.py
test.py
equihash/__init__.py
pyequihash.egg-info/PKG-INFO
pyequihash.egg-info/SOURCES.txt
pyequihash.egg-info/dependency_links.txt
pyequihash.egg-info/top_level.txt