Metadata-Version: 2.1
Name: pyequihash
Version: 0.2
Summary: python bindings for libequihash
Home-page: https://github.com/stef/equihash/python
Author: Stefan Marsiske
Author-email: sphinx@ctrlc.hu
License: GPLv3
Classifier: Development Status :: 4 - Beta
Classifier: License :: OSI Approved :: GNU General Public License v3 or later (GPLv3+)
Classifier: Topic :: Security :: Cryptography
Classifier: Topic :: Security
License-File: LICENSE
